<?xml version="1.0" ?>
<catalog xmlns="urn:oasis:names:tc:entity:xmlns:xml:catalog">

<!-- system systemId= is for ditac's Xerces -->
<!-- uri name= is for XXE's Xerces -->

<group xml:base="base/xsd/">
  <system systemId="urn:oasis:names:tc:dita:xsd:topicMod.xsd:1.x"
          uri="topicMod.xsd"/>
  <system systemId="urn:oasis:names:tc:dita:xsd:topicMod.xsd:1.2"
          uri="topicMod.xsd"/>

  <system systemId="urn:oasis:names:tc:dita:xsd:basetopic.xsd:1.x"
          uri="basetopic.xsd"/>
  <system systemId="urn:oasis:names:tc:dita:xsd:basetopic.xsd:1.2"
          uri="basetopic.xsd"/>

  <system systemId="urn:oasis:names:tc:dita:xsd:topicGrp.xsd:1.x"
          uri="topicGrp.xsd"/>
  <system systemId="urn:oasis:names:tc:dita:xsd:topicGrp.xsd:1.2"
          uri="topicGrp.xsd"/>

  <system systemId="urn:oasis:names:tc:dita:xsd:tblDeclMod.xsd:1.x"
          uri="tblDeclMod.xsd"/>
  <system systemId="urn:oasis:names:tc:dita:xsd:tblDeclMod.xsd:1.2"
          uri="tblDeclMod.xsd"/>

  <system systemId="urn:oasis:names:tc:dita:xsd:tblDeclGrp.xsd:1.x"
          uri="tblDeclGrp.xsd"/>
  <system systemId="urn:oasis:names:tc:dita:xsd:tblDeclGrp.xsd:1.2"
          uri="tblDeclGrp.xsd"/>

  <system systemId="urn:oasis:names:tc:dita:xsd:metaDeclMod.xsd:1.x"
          uri="metaDeclMod.xsd"/>
  <system systemId="urn:oasis:names:tc:dita:xsd:metaDeclMod.xsd:1.2"
          uri="metaDeclMod.xsd"/>

  <system systemId="urn:oasis:names:tc:dita:xsd:metaDeclGrp.xsd:1.x"
          uri="metaDeclGrp.xsd"/>
  <system systemId="urn:oasis:names:tc:dita:xsd:metaDeclGrp.xsd:1.2"
          uri="metaDeclGrp.xsd"/>

  <system systemId="urn:oasis:names:tc:dita:xsd:mapMod.xsd:1.x"
          uri="mapMod.xsd"/>
  <system systemId="urn:oasis:names:tc:dita:xsd:mapMod.xsd:1.2"
          uri="mapMod.xsd"/>

  <system systemId="urn:oasis:names:tc:dita:xsd:basemap.xsd:1.x"
          uri="basemap.xsd"/>
  <system systemId="urn:oasis:names:tc:dita:xsd:basemap.xsd:1.2"
          uri="basemap.xsd"/>

  <system systemId="urn:oasis:names:tc:dita:xsd:mapGrp.xsd:1.x"
          uri="mapGrp.xsd"/>
  <system systemId="urn:oasis:names:tc:dita:xsd:mapGrp.xsd:1.2"
          uri="mapGrp.xsd"/>

  <system systemId="urn:oasis:names:tc:dita:xsd:mapGroupMod.xsd:1.x"
          uri="mapGroupMod.xsd"/>
  <system systemId="urn:oasis:names:tc:dita:xsd:mapGroupMod.xsd:1.2"
          uri="mapGroupMod.xsd"/>

  <system systemId="urn:oasis:names:tc:dita:xsd:highlightDomain.xsd:1.x"
          uri="highlightDomain.xsd"/>
  <system systemId="urn:oasis:names:tc:dita:xsd:highlightDomain.xsd:1.2"
          uri="highlightDomain.xsd"/>

  <system systemId="urn:oasis:names:tc:dita:xsd:utilitiesDomain.xsd:1.x"
          uri="utilitiesDomain.xsd"/>
  <system systemId="urn:oasis:names:tc:dita:xsd:utilitiesDomain.xsd:1.2"
          uri="utilitiesDomain.xsd"/>

  <system systemId="urn:oasis:names:tc:dita:xsd:indexingDomain.xsd:1.x"
          uri="indexingDomain.xsd"/>
  <system systemId="urn:oasis:names:tc:dita:xsd:indexingDomain.xsd:1.2"
          uri="indexingDomain.xsd"/>

  <system systemId="urn:oasis:names:tc:dita:xsd:hazardstatementDomain.xsd:1.x"
          uri="hazardstatementDomain.xsd"/>
  <system systemId="urn:oasis:names:tc:dita:xsd:hazardstatementDomain.xsd:1.2"
          uri="hazardstatementDomain.xsd"/>

  <system systemId="urn:oasis:names:tc:dita:xsd:delayResolutionDomain.xsd:1.x"
          uri="delayResolutionDomain.xsd"/>
  <system systemId="urn:oasis:names:tc:dita:xsd:delayResolutionDomain.xsd:1.2"
          uri="delayResolutionDomain.xsd"/>

  <system systemId="urn:oasis:names:tc:dita:xsd:ditaarch.xsd:1.x"
          uri="ditaarch.xsd"/>
  <system systemId="urn:oasis:names:tc:dita:xsd:ditaarch.xsd:1.2"
          uri="ditaarch.xsd"/>

  <system systemId="urn:oasis:names:tc:dita:xsd:xml.xsd:1.x"
          uri="xml.xsd"/>
  <system systemId="urn:oasis:names:tc:dita:xsd:xml.xsd:1.2"
          uri="xml.xsd"/>

  <system systemId="urn:oasis:names:tc:dita:xsd:commonElementMod.xsd:1.2"
          uri="commonElementMod.xsd"/>
  <system systemId="urn:oasis:names:tc:dita:xsd:commonElementMod.xsd:1.2"
          uri="commonElementMod.xsd"/>
  <system systemId="urn:oasis:names:tc:dita:xsd:commonElementMod.xsd:1.2"
          uri="commonElementMod.xsd"/>

  <system systemId="urn:oasis:names:tc:dita:xsd:commonElementGrp.xsd:1.x"
          uri="commonElementGrp.xsd"/>
  <system systemId="urn:oasis:names:tc:dita:xsd:commonElementGrp.xsd:1.2"
          uri="commonElementGrp.xsd"/>

  <uri name="urn:oasis:names:tc:dita:xsd:topicMod.xsd:1.x"
       uri="topicMod.xsd"/>
  <uri name="urn:oasis:names:tc:dita:xsd:topicMod.xsd:1.2"
       uri="topicMod.xsd"/>

  <uri name="urn:oasis:names:tc:dita:xsd:basetopic.xsd:1.x"
       uri="basetopic.xsd"/>
  <uri name="urn:oasis:names:tc:dita:xsd:basetopic.xsd:1.2"
       uri="basetopic.xsd"/>

  <uri name="urn:oasis:names:tc:dita:xsd:topicGrp.xsd:1.x"
       uri="topicGrp.xsd"/>
  <uri name="urn:oasis:names:tc:dita:xsd:topicGrp.xsd:1.2"
       uri="topicGrp.xsd"/>

  <uri name="urn:oasis:names:tc:dita:xsd:tblDeclMod.xsd:1.x"
       uri="tblDeclMod.xsd"/>
  <uri name="urn:oasis:names:tc:dita:xsd:tblDeclMod.xsd:1.2"
       uri="tblDeclMod.xsd"/>

  <uri name="urn:oasis:names:tc:dita:xsd:tblDeclGrp.xsd:1.x"
       uri="tblDeclGrp.xsd"/>
  <uri name="urn:oasis:names:tc:dita:xsd:tblDeclGrp.xsd:1.2"
       uri="tblDeclGrp.xsd"/>

  <uri name="urn:oasis:names:tc:dita:xsd:metaDeclMod.xsd:1.x"
       uri="metaDeclMod.xsd"/>
  <uri name="urn:oasis:names:tc:dita:xsd:metaDeclMod.xsd:1.2"
       uri="metaDeclMod.xsd"/>

  <uri name="urn:oasis:names:tc:dita:xsd:metaDeclGrp.xsd:1.x"
       uri="metaDeclGrp.xsd"/>
  <uri name="urn:oasis:names:tc:dita:xsd:metaDeclGrp.xsd:1.2"
       uri="metaDeclGrp.xsd"/>

  <uri name="urn:oasis:names:tc:dita:xsd:mapMod.xsd:1.x"
       uri="mapMod.xsd"/>
  <uri name="urn:oasis:names:tc:dita:xsd:mapMod.xsd:1.2"
       uri="mapMod.xsd"/>

  <uri name="urn:oasis:names:tc:dita:xsd:basemap.xsd:1.x"
       uri="basemap.xsd"/>
  <uri name="urn:oasis:names:tc:dita:xsd:basemap.xsd:1.2"
       uri="basemap.xsd"/>

  <uri name="urn:oasis:names:tc:dita:xsd:mapGrp.xsd:1.x"
       uri="mapGrp.xsd"/>
  <uri name="urn:oasis:names:tc:dita:xsd:mapGrp.xsd:1.2"
       uri="mapGrp.xsd"/>

  <uri name="urn:oasis:names:tc:dita:xsd:mapGroupMod.xsd:1.x"
       uri="mapGroupMod.xsd"/>
  <uri name="urn:oasis:names:tc:dita:xsd:mapGroupMod.xsd:1.2"
       uri="mapGroupMod.xsd"/>

  <uri name="urn:oasis:names:tc:dita:xsd:highlightDomain.xsd:1.x"
       uri="highlightDomain.xsd"/>
  <uri name="urn:oasis:names:tc:dita:xsd:highlightDomain.xsd:1.2"
       uri="highlightDomain.xsd"/>

  <uri name="urn:oasis:names:tc:dita:xsd:utilitiesDomain.xsd:1.x"
       uri="utilitiesDomain.xsd"/>
  <uri name="urn:oasis:names:tc:dita:xsd:utilitiesDomain.xsd:1.2"
       uri="utilitiesDomain.xsd"/>

  <uri name="urn:oasis:names:tc:dita:xsd:indexingDomain.xsd:1.x"
       uri="indexingDomain.xsd"/>
  <uri name="urn:oasis:names:tc:dita:xsd:indexingDomain.xsd:1.2"
       uri="indexingDomain.xsd"/>

  <uri name="urn:oasis:names:tc:dita:xsd:hazardstatementDomain.xsd:1.x"
       uri="hazardstatementDomain.xsd"/>
  <uri name="urn:oasis:names:tc:dita:xsd:hazardstatementDomain.xsd:1.2"
       uri="hazardstatementDomain.xsd"/>

  <uri name="urn:oasis:names:tc:dita:xsd:delayResolutionDomain.xsd:1.x"
       uri="delayResolutionDomain.xsd"/>
  <uri name="urn:oasis:names:tc:dita:xsd:delayResolutionDomain.xsd:1.2"
       uri="delayResolutionDomain.xsd"/>

  <uri name="urn:oasis:names:tc:dita:xsd:ditaarch.xsd:1.x"
       uri="ditaarch.xsd"/>
  <uri name="urn:oasis:names:tc:dita:xsd:ditaarch.xsd:1.2"
       uri="ditaarch.xsd"/>

  <uri name="urn:oasis:names:tc:dita:xsd:xml.xsd:1.x"
       uri="xml.xsd"/>
  <uri name="urn:oasis:names:tc:dita:xsd:xml.xsd:1.2"
       uri="xml.xsd"/>

  <uri name="urn:oasis:names:tc:dita:xsd:commonElementMod.xsd:1.2"
       uri="commonElementMod.xsd"/>
  <uri name="urn:oasis:names:tc:dita:xsd:commonElementMod.xsd:1.2"
       uri="commonElementMod.xsd"/>
  <uri name="urn:oasis:names:tc:dita:xsd:commonElementMod.xsd:1.2"
       uri="commonElementMod.xsd"/>

  <uri name="urn:oasis:names:tc:dita:xsd:commonElementGrp.xsd:1.x"
       uri="commonElementGrp.xsd"/>
  <uri name="urn:oasis:names:tc:dita:xsd:commonElementGrp.xsd:1.2"
       uri="commonElementGrp.xsd"/>
</group>

<!-- Document types and modules used by the Technical Content package -->
<group xml:base="technicalContent/xsd/">
  <system systemId="urn:oasis:names:tc:dita:xsd:topic.xsd:1.x"
          uri="topic.xsd"/>
  <system systemId="urn:oasis:names:tc:dita:xsd:topic.xsd:1.2"
          uri="topic.xsd"/>

  <system systemId="urn:oasis:names:tc:dita:xsd:map.xsd:1.x"
          uri="map.xsd"/>
  <system systemId="urn:oasis:names:tc:dita:xsd:map.xsd:1.2"
          uri="map.xsd"/>

  <system systemId="urn:oasis:names:tc:dita:xsd:ditabase.xsd:1.x"
          uri="ditabase.xsd"/>
  <system systemId="urn:oasis:names:tc:dita:xsd:ditabase.xsd:1.2"
          uri="ditabase.xsd"/>

  <system systemId="urn:oasis:names:tc:dita:xsd:ditabaseMod.xsd:1.x"
          uri="ditabaseMod.xsd"/>
  <system systemId="urn:oasis:names:tc:dita:xsd:ditabaseMod.xsd:1.2"
          uri="ditabaseMod.xsd"/>

  <system systemId="urn:oasis:names:tc:dita:xsd:concept.xsd:1.x"
          uri="concept.xsd"/>
  <system systemId="urn:oasis:names:tc:dita:xsd:concept.xsd:1.2"
          uri="concept.xsd"/>

  <system systemId="urn:oasis:names:tc:dita:xsd:conceptMod.xsd:1.x"
          uri="conceptMod.xsd"/>
  <system systemId="urn:oasis:names:tc:dita:xsd:conceptMod.xsd:1.2"
          uri="conceptMod.xsd"/>

  <system systemId="urn:oasis:names:tc:dita:xsd:conceptGrp.xsd:1.x"
          uri="conceptGrp.xsd"/>
  <system systemId="urn:oasis:names:tc:dita:xsd:conceptGrp.xsd:1.2"
          uri="conceptGrp.xsd"/>

  <system systemId="urn:oasis:names:tc:dita:xsd:reference.xsd:1.x"
          uri="reference.xsd"/>
  <system systemId="urn:oasis:names:tc:dita:xsd:reference.xsd:1.2"
          uri="reference.xsd"/>

  <system systemId="urn:oasis:names:tc:dita:xsd:referenceMod.xsd:1.x"
          uri="referenceMod.xsd"/>
  <system systemId="urn:oasis:names:tc:dita:xsd:referenceMod.xsd:1.2"
          uri="referenceMod.xsd"/>

  <system systemId="urn:oasis:names:tc:dita:xsd:referenceGrp.xsd:1.x"
          uri="referenceGrp.xsd"/>
  <system systemId="urn:oasis:names:tc:dita:xsd:referenceGrp.xsd:1.2"
          uri="referenceGrp.xsd"/>

  <system systemId="urn:oasis:names:tc:dita:xsd:task.xsd:1.x"
          uri="task.xsd"/>
  <system systemId="urn:oasis:names:tc:dita:xsd:task.xsd:1.2"
          uri="task.xsd"/>

  <system systemId="urn:oasis:names:tc:dita:xsd:generalTask.xsd:1.x"
          uri="generalTask.xsd"/>
  <system systemId="urn:oasis:names:tc:dita:xsd:generalTask.xsd:1.2"
          uri="generalTask.xsd"/>

  <system systemId="urn:oasis:names:tc:dita:xsd:taskMod.xsd:1.x"
          uri="taskMod.xsd"/>
  <system systemId="urn:oasis:names:tc:dita:xsd:taskMod.xsd:1.2"
          uri="taskMod.xsd"/>

  <system systemId="urn:oasis:names:tc:dita:xsd:strictTaskbodyConstraintMod.xsd:1.x"
          uri="strictTaskbodyConstraintMod.xsd"/>
  <system systemId="urn:oasis:names:tc:dita:xsd:strictTaskbodyConstraintMod.xsd:1.2"
          uri="strictTaskbodyConstraintMod.xsd"/>

  <system systemId="urn:oasis:names:tc:dita:xsd:taskGrp.xsd:1.x"
          uri="taskGrp.xsd"/>
  <system systemId="urn:oasis:names:tc:dita:xsd:taskGrp.xsd:1.2"
          uri="taskGrp.xsd"/>

  <system systemId="urn:oasis:names:tc:dita:xsd:glossary.xsd:1.x"
          uri="glossary.xsd"/>
  <system systemId="urn:oasis:names:tc:dita:xsd:glossary.xsd:1.2"
          uri="glossary.xsd"/>

  <system systemId="urn:oasis:names:tc:dita:xsd:glossaryMod.xsd:1.x"
          uri="glossaryMod.xsd"/>
  <system systemId="urn:oasis:names:tc:dita:xsd:glossaryMod.xsd:1.2"
          uri="glossaryMod.xsd"/>

  <system systemId="urn:oasis:names:tc:dita:xsd:glossaryGrp.xsd:1.x"
          uri="glossaryGrp.xsd"/>
  <system systemId="urn:oasis:names:tc:dita:xsd:glossaryGrp.xsd:1.2"
          uri="glossaryGrp.xsd"/>

  <system systemId="urn:oasis:names:tc:dita:xsd:glossentry.xsd:1.x"
          uri="glossentry.xsd"/>
  <system systemId="urn:oasis:names:tc:dita:xsd:glossentry.xsd:1.2"
          uri="glossentry.xsd"/>

  <system systemId="urn:oasis:names:tc:dita:xsd:glossentryMod.xsd:1.x"
          uri="glossentryMod.xsd"/>
  <system systemId="urn:oasis:names:tc:dita:xsd:glossentryMod.xsd:1.2"
          uri="glossentryMod.xsd"/>

  <system systemId="urn:oasis:names:tc:dita:xsd:glossentryGrp.xsd:1.x"
          uri="glossentryGrp.xsd"/>
  <system systemId="urn:oasis:names:tc:dita:xsd:glossentryGrp.xsd:1.2"
          uri="glossentryGrp.xsd"/>

  <system systemId="urn:oasis:names:tc:dita:xsd:glossarygroup.xsd:1.x"
          uri="glossgroup.xsd"/>
  <system systemId="urn:oasis:names:tc:dita:xsd:glossarygroup.xsd:1.2"
          uri="glossgroup.xsd"/>

  <system systemId="urn:oasis:names:tc:dita:xsd:glossgroupMod.xsd:1.x"
          uri="glossgroupMod.xsd"/>
  <system systemId="urn:oasis:names:tc:dita:xsd:glossgroupMod.xsd:1.2"
          uri="glossgroupMod.xsd"/>

  <system systemId="urn:oasis:names:tc:dita:xsd:glossgroupGrp.xsd:1.x"
          uri="glossgroupGrp.xsd"/>
  <system systemId="urn:oasis:names:tc:dita:xsd:glossgroupGrp.xsd:1.2"
          uri="glossgroupGrp.xsd"/>

  <system systemId="urn:oasis:names:tc:dita:xsd:softwareDomain.xsd:1.x"
          uri="softwareDomain.xsd"/>
  <system systemId="urn:oasis:names:tc:dita:xsd:softwareDomain.xsd:1.2"
       uri="softwareDomain.xsd"/>

  <system systemId="urn:oasis:names:tc:dita:xsd:programmingDomain.xsd:1.x"
          uri="programmingDomain.xsd"/>
  <system systemId="urn:oasis:names:tc:dita:xsd:programmingDomain.xsd:1.2"
          uri="programmingDomain.xsd"/>

  <system systemId="urn:oasis:names:tc:dita:xsd:uiDomain.xsd:1.x"
          uri="uiDomain.xsd"/>
  <system systemId="urn:oasis:names:tc:dita:xsd:uiDomain.xsd:1.2"
          uri="uiDomain.xsd"/>

  <system systemId="urn:oasis:names:tc:dita:xsd:glossrefDomain.xsd:1.x"
          uri="glossrefDomain.xsd"/>
  <system systemId="urn:oasis:names:tc:dita:xsd:glossrefDomain.xsd:1.2"
          uri="glossrefDomain.xsd"/>

  <system systemId="urn:oasis:names:tc:dita:xsd:abbreviateDomain.xsd:1.x"
          uri="abbreviateDomain.xsd"/>
  <system systemId="urn:oasis:names:tc:dita:xsd:abbreviateDomain.xsd:1.2"
          uri="abbreviateDomain.xsd"/>

  <system systemId="urn:oasis:names:tc:dita:xsd:taskreqDomain.xsd:1.x"
          uri="taskreqDomain.xsd"/>
  <system systemId="urn:oasis:names:tc:dita:xsd:taskreqDomain.xsd:1.2"
          uri="taskreqDomain.xsd"/>

  <uri name="urn:oasis:names:tc:dita:xsd:topic.xsd:1.x"
       uri="topic.xsd"/>
  <uri name="urn:oasis:names:tc:dita:xsd:topic.xsd:1.2"
       uri="topic.xsd"/>

  <uri name="urn:oasis:names:tc:dita:xsd:map.xsd:1.x"
       uri="map.xsd"/>
  <uri name="urn:oasis:names:tc:dita:xsd:map.xsd:1.2"
       uri="map.xsd"/>

  <uri name="urn:oasis:names:tc:dita:xsd:ditabase.xsd:1.x"
       uri="ditabase.xsd"/>
  <uri name="urn:oasis:names:tc:dita:xsd:ditabase.xsd:1.2"
       uri="ditabase.xsd"/>

  <uri name="urn:oasis:names:tc:dita:xsd:ditabaseMod.xsd:1.x"
       uri="ditabaseMod.xsd"/>
  <uri name="urn:oasis:names:tc:dita:xsd:ditabaseMod.xsd:1.2"
       uri="ditabaseMod.xsd"/>

  <uri name="urn:oasis:names:tc:dita:xsd:concept.xsd:1.x"
       uri="concept.xsd"/>
  <uri name="urn:oasis:names:tc:dita:xsd:concept.xsd:1.2"
       uri="concept.xsd"/>

  <uri name="urn:oasis:names:tc:dita:xsd:conceptMod.xsd:1.x"
       uri="conceptMod.xsd"/>
  <uri name="urn:oasis:names:tc:dita:xsd:conceptMod.xsd:1.2"
       uri="conceptMod.xsd"/>

  <uri name="urn:oasis:names:tc:dita:xsd:conceptGrp.xsd:1.x"
       uri="conceptGrp.xsd"/>
  <uri name="urn:oasis:names:tc:dita:xsd:conceptGrp.xsd:1.2"
       uri="conceptGrp.xsd"/>

  <uri name="urn:oasis:names:tc:dita:xsd:reference.xsd:1.x"
       uri="reference.xsd"/>
  <uri name="urn:oasis:names:tc:dita:xsd:reference.xsd:1.2"
       uri="reference.xsd"/>

  <uri name="urn:oasis:names:tc:dita:xsd:referenceMod.xsd:1.x"
       uri="referenceMod.xsd"/>
  <uri name="urn:oasis:names:tc:dita:xsd:referenceMod.xsd:1.2"
       uri="referenceMod.xsd"/>

  <uri name="urn:oasis:names:tc:dita:xsd:referenceGrp.xsd:1.x"
       uri="referenceGrp.xsd"/>
  <uri name="urn:oasis:names:tc:dita:xsd:referenceGrp.xsd:1.2"
       uri="referenceGrp.xsd"/>

  <uri name="urn:oasis:names:tc:dita:xsd:task.xsd:1.x"
       uri="task.xsd"/>
  <uri name="urn:oasis:names:tc:dita:xsd:task.xsd:1.2"
       uri="task.xsd"/>

  <uri name="urn:oasis:names:tc:dita:xsd:generalTask.xsd:1.x"
       uri="generalTask.xsd"/>
  <uri name="urn:oasis:names:tc:dita:xsd:generalTask.xsd:1.2"
       uri="generalTask.xsd"/>

  <uri name="urn:oasis:names:tc:dita:xsd:taskMod.xsd:1.x"
       uri="taskMod.xsd"/>
  <uri name="urn:oasis:names:tc:dita:xsd:taskMod.xsd:1.2"
       uri="taskMod.xsd"/>

  <uri name="urn:oasis:names:tc:dita:xsd:strictTaskbodyConstraintMod.xsd:1.x"
       uri="strictTaskbodyConstraintMod.xsd"/>
  <uri name="urn:oasis:names:tc:dita:xsd:strictTaskbodyConstraintMod.xsd:1.2"
       uri="strictTaskbodyConstraintMod.xsd"/>

  <uri name="urn:oasis:names:tc:dita:xsd:taskGrp.xsd:1.x"
       uri="taskGrp.xsd"/>
  <uri name="urn:oasis:names:tc:dita:xsd:taskGrp.xsd:1.2"
       uri="taskGrp.xsd"/>

  <uri name="urn:oasis:names:tc:dita:xsd:glossary.xsd:1.x"
       uri="glossary.xsd"/>
  <uri name="urn:oasis:names:tc:dita:xsd:glossary.xsd:1.2"
       uri="glossary.xsd"/>

  <uri name="urn:oasis:names:tc:dita:xsd:glossaryMod.xsd:1.x"
       uri="glossaryMod.xsd"/>
  <uri name="urn:oasis:names:tc:dita:xsd:glossaryMod.xsd:1.2"
       uri="glossaryMod.xsd"/>

  <uri name="urn:oasis:names:tc:dita:xsd:glossaryGrp.xsd:1.x"
       uri="glossaryGrp.xsd"/>
  <uri name="urn:oasis:names:tc:dita:xsd:glossaryGrp.xsd:1.2"
       uri="glossaryGrp.xsd"/>

  <uri name="urn:oasis:names:tc:dita:xsd:glossentry.xsd:1.x"
       uri="glossentry.xsd"/>
  <uri name="urn:oasis:names:tc:dita:xsd:glossentry.xsd:1.2"
       uri="glossentry.xsd"/>

  <uri name="urn:oasis:names:tc:dita:xsd:glossentryMod.xsd:1.x"
       uri="glossentryMod.xsd"/>
  <uri name="urn:oasis:names:tc:dita:xsd:glossentryMod.xsd:1.2"
       uri="glossentryMod.xsd"/>

  <uri name="urn:oasis:names:tc:dita:xsd:glossentryGrp.xsd:1.x"
       uri="glossentryGrp.xsd"/>
  <uri name="urn:oasis:names:tc:dita:xsd:glossentryGrp.xsd:1.2"
       uri="glossentryGrp.xsd"/>

  <uri name="urn:oasis:names:tc:dita:xsd:glossarygroup.xsd:1.x"
       uri="glossgroup.xsd"/>
  <uri name="urn:oasis:names:tc:dita:xsd:glossarygroup.xsd:1.2"
       uri="glossgroup.xsd"/>

  <uri name="urn:oasis:names:tc:dita:xsd:glossgroupMod.xsd:1.x"
       uri="glossgroupMod.xsd"/>
  <uri name="urn:oasis:names:tc:dita:xsd:glossgroupMod.xsd:1.2"
       uri="glossgroupMod.xsd"/>

  <uri name="urn:oasis:names:tc:dita:xsd:glossgroupGrp.xsd:1.x"
       uri="glossgroupGrp.xsd"/>
  <uri name="urn:oasis:names:tc:dita:xsd:glossgroupGrp.xsd:1.2"
       uri="glossgroupGrp.xsd"/>

  <uri name="urn:oasis:names:tc:dita:xsd:softwareDomain.xsd:1.x"
       uri="softwareDomain.xsd"/>
  <uri name="urn:oasis:names:tc:dita:xsd:softwareDomain.xsd:1.2"
       uri="softwareDomain.xsd"/>

  <uri name="urn:oasis:names:tc:dita:xsd:programmingDomain.xsd:1.x"
       uri="programmingDomain.xsd"/>
  <uri name="urn:oasis:names:tc:dita:xsd:programmingDomain.xsd:1.2"
       uri="programmingDomain.xsd"/>

  <uri name="urn:oasis:names:tc:dita:xsd:uiDomain.xsd:1.x"
       uri="uiDomain.xsd"/>
  <uri name="urn:oasis:names:tc:dita:xsd:uiDomain.xsd:1.2"
       uri="uiDomain.xsd"/>

  <uri name="urn:oasis:names:tc:dita:xsd:glossrefDomain.xsd:1.x"
       uri="glossrefDomain.xsd"/>
  <uri name="urn:oasis:names:tc:dita:xsd:glossrefDomain.xsd:1.2"
       uri="glossrefDomain.xsd"/>

  <uri name="urn:oasis:names:tc:dita:xsd:abbreviateDomain.xsd:1.x"
       uri="abbreviateDomain.xsd"/>
  <uri name="urn:oasis:names:tc:dita:xsd:abbreviateDomain.xsd:1.2"
       uri="abbreviateDomain.xsd"/>

  <uri name="urn:oasis:names:tc:dita:xsd:taskreqDomain.xsd:1.x"
       uri="taskreqDomain.xsd"/>
  <uri name="urn:oasis:names:tc:dita:xsd:taskreqDomain.xsd:1.2"
       uri="taskreqDomain.xsd"/>
</group>

<!-- Bookmap document type and module -->
<group xml:base="bookmap/xsd/">
  <system systemId="urn:oasis:names:tc:dita:xsd:bookmap.xsd:1.x"
          uri="bookmap.xsd"/>
  <system systemId="urn:oasis:names:tc:dita:xsd:bookmap.xsd:1.2"
          uri="bookmap.xsd"/>

  <system systemId="urn:oasis:names:tc:dita:xsd:bookmapMod.xsd:1.x"
          uri="bookmapMod.xsd"/>
  <system systemId="urn:oasis:names:tc:dita:xsd:bookmapMod.xsd:1.2"
          uri="bookmapMod.xsd"/>

  <system systemId="urn:oasis:names:tc:dita:xsd:bookmapGrp.xsd:1.x"
          uri="bookmapGrp.xsd"/>
  <system systemId="urn:oasis:names:tc:dita:xsd:bookmapGrp.xsd:1.2"
          uri="bookmapGrp.xsd"/>

  <uri name="urn:oasis:names:tc:dita:xsd:bookmap.xsd:1.x"
       uri="bookmap.xsd"/>
  <uri name="urn:oasis:names:tc:dita:xsd:bookmap.xsd:1.2"
       uri="bookmap.xsd"/>

  <uri name="urn:oasis:names:tc:dita:xsd:bookmapMod.xsd:1.x"
       uri="bookmapMod.xsd"/>
  <uri name="urn:oasis:names:tc:dita:xsd:bookmapMod.xsd:1.2"
       uri="bookmapMod.xsd"/>

  <uri name="urn:oasis:names:tc:dita:xsd:bookmapGrp.xsd:1.x"
       uri="bookmapGrp.xsd"/>
  <uri name="urn:oasis:names:tc:dita:xsd:bookmapGrp.xsd:1.2"
       uri="bookmapGrp.xsd"/>
</group>

<!-- Domain for representing XNAL address information -->
<group xml:base="xnal/xsd/">
  <system systemId="urn:oasis:names:tc:dita:xsd:xnalDomain.xsd:1.x"
          uri="xnalDomain.xsd"/>
  <system systemId="urn:oasis:names:tc:dita:xsd:xnalDomain.xsd:1.2"
          uri="xnalDomain.xsd"/>

  <uri name="urn:oasis:names:tc:dita:xsd:xnalDomain.xsd:1.x"
       uri="xnalDomain.xsd"/>
  <uri name="urn:oasis:names:tc:dita:xsd:xnalDomain.xsd:1.2"
       uri="xnalDomain.xsd"/>
</group>

<!-- Subject scheme package for controlled vocabularies -->
<group xml:base="subjectScheme/xsd/">
   <system systemId="urn:oasis:names:tc:dita:spec:classification:xsd:subjectScheme.xsd:1.x"
           uri="subjectScheme.xsd"/>
   <system systemId="urn:oasis:names:tc:dita:spec:classification:xsd:subjectScheme.xsd:1.2"
           uri="subjectScheme.xsd"/>

   <system systemId="urn:oasis:names:tc:dita:spec:classification:xsd:subjectSchemeMod.xsd:1.x"
           uri="subjectSchemeMod.xsd"/>
   <system systemId="urn:oasis:names:tc:dita:spec:classification:xsd:subjectSchemeMod.xsd:1.2"
           uri="subjectSchemeMod.xsd"/>

   <system systemId="urn:oasis:names:tc:dita:spec:classification:xsd:subjectSchemeGrp.xsd:1.x"
           uri="subjectSchemeGrp.xsd"/>
   <system systemId="urn:oasis:names:tc:dita:spec:classification:xsd:subjectSchemeGrp.xsd:1.2"
           uri="subjectSchemeGrp.xsd"/>

   <system systemId="urn:oasis:names:tc:dita:spec:classification:xsd:classifyMap.xsd:1.x"
           uri="classifyMap.xsd"/>
   <system systemId="urn:oasis:names:tc:dita:spec:classification:xsd:classifyMap.xsd:1.2"
           uri="classifyMap.xsd"/>

   <system systemId="urn:oasis:names:tc:dita:spec:classification:xsd:classifyDomain.xsd:1.x"
           uri="classifyDomain.xsd"/>
   <system systemId="urn:oasis:names:tc:dita:spec:classification:xsd:classifyDomain.xsd:1.2"
           uri="classifyDomain.xsd"/>

   <uri name="urn:oasis:names:tc:dita:spec:classification:xsd:subjectScheme.xsd:1.x"
        uri="subjectScheme.xsd"/>
   <uri name="urn:oasis:names:tc:dita:spec:classification:xsd:subjectScheme.xsd:1.2"
        uri="subjectScheme.xsd"/>

   <uri name="urn:oasis:names:tc:dita:spec:classification:xsd:subjectSchemeMod.xsd:1.x"
        uri="subjectSchemeMod.xsd"/>
   <uri name="urn:oasis:names:tc:dita:spec:classification:xsd:subjectSchemeMod.xsd:1.2"
        uri="subjectSchemeMod.xsd"/>

   <uri name="urn:oasis:names:tc:dita:spec:classification:xsd:subjectSchemeGrp.xsd:1.x"
        uri="subjectSchemeGrp.xsd"/>
   <uri name="urn:oasis:names:tc:dita:spec:classification:xsd:subjectSchemeGrp.xsd:1.2"
        uri="subjectSchemeGrp.xsd"/>

   <uri name="urn:oasis:names:tc:dita:spec:classification:xsd:classifyMap.xsd:1.x"
        uri="classifyMap.xsd"/>
   <uri name="urn:oasis:names:tc:dita:spec:classification:xsd:classifyMap.xsd:1.2"
        uri="classifyMap.xsd"/>

   <uri name="urn:oasis:names:tc:dita:spec:classification:xsd:classifyDomain.xsd:1.x"
        uri="classifyDomain.xsd"/>
   <uri name="urn:oasis:names:tc:dita:spec:classification:xsd:classifyDomain.xsd:1.2"
        uri="classifyDomain.xsd"/>
</group>

<!-- DITAVal package for conditional processing -->
<group xml:base="ditaval/xsd/">
  <system systemId="urn:oasis:names:tc:dita:xsd:ditaval.xsd:1.x" 
          uri="ditaval.xsd"/>
  <system systemId="urn:oasis:names:tc:dita:xsd:ditaval.xsd:1.2" 
          uri="ditaval.xsd"/>

  <uri name="urn:oasis:names:tc:dita:xsd:ditaval.xsd:1.x" 
       uri="ditaval.xsd"/>
  <uri name="urn:oasis:names:tc:dita:xsd:ditaval.xsd:1.2" 
       uri="ditaval.xsd"/>
</group>

</catalog>
